{"expireTime":9007200882399420000,"key":"35d191193dfb2ba3c7344686eddb93a7","val":{"name":"IMAGE_PROCESSING","inputPaths":["C:/Users/Eddy/Documents/headlesWall/.cache/caches/gatsby-source-wordpress/9b8a15fa56d45e65253f4120ca5e4765/header_v3-copy.png"],"outputDir":"C:/Users/Eddy/Documents/headlesWall/public/static/da39cc4deb8016b34aeb30e5402f957c","args":{"isLazy":false,"operations":[{"outputPath":"200e5\\header_v3-copy.png","args":{"width":480,"cropFocus":17,"toFormat":"png","quality":90,"fit":"cover","background":"rgba(0,0,0,1)"}},{"outputPath":"2ada3\\header_v3-copy.png","args":{"width":960,"cropFocus":17,"toFormat":"png","quality":90,"fit":"cover","background":"rgba(0,0,0,1)"}},{"outputPath":"c608a\\header_v3-copy.png","args":{"width":1920,"cropFocus":17,"toFormat":"png","quality":90,"fit":"cover","background":"rgba(0,0,0,1)"}}],"pluginOptions":{"base64Width":20,"forceBase64Format":"","useMozJpeg":false,"stripMetadata":true,"lazyImageGeneration":true,"defaultQuality":50,"failOnError":true,"plugins":[]}}}}